{
  "type": "FeatureCollection",
  "features": [
    {
      "type": "Feature",
      "properties": {
        "name": "hello1",
        "description": "D189"
      },
      "geometry": {
        "type": "Point",
        "coordinates": [
          37.571868896484375,
          55.81671548420953
        ]
      }
    },
    {
      "type": "Feature",
      "properties": {
        "name": "Hello2",
        "description": "D2"
      },
      "geometry": {
        "type": "Point",
        "coordinates": [
          37.514190673828125,
          55.73020335605107
        ]
      }
    },
    {
      "type": "Feature",
      "properties": {
        "name": "hello3",
        "description": "D3"
      },
      "geometry": {
        "type": "Point",
        "coordinates": [
          37.6226806640625,
          55.75532709909638
        ]
      }
    },
    {
      "type": "Feature",
      "properties": {
        "name": "hello4",
        "description": "D4"
      },
      "geometry": {
        "type": "Point",
        "coordinates": [
          37.529296875,
          55.78197922246133
        ]
      }
    }
  ]
}